pygnews/__init__.py
pygnews/constants.py
pygnews/fetcher.py
pygnews/helpers.py
pygnews-0.1.1.dist-info/LICENSE
pygnews-0.1.1.dist-info/METADATA
pygnews-0.1.1.dist-info/WHEEL
pygnews-0.1.1.dist-info/top_level.txt
pygnews-0.1.1.dist-info/RECORD
