Metadata-Version: 2.1
Name: pygnews
Version: 0.1.1
Summary: Python library for scrapping Google news feeds
Home-page: https://github.com/Law101/pygnews
Author: Lawrence Okegbemi
Author-email: lawrencebolu@gmail.com
License: UNKNOWN
Project-URL: Documentation, https://law101.github.io/pygnews/
Project-URL: Bug Tracker, https://github.com/Law101/pygnews/issues
Platform: UNKNOWN
Classifier: Programming Language :: Python :: 3
Classifier: Programming Language :: Python :: 3.2
Classifier: Programming Language :: Python :: 3.3
Classifier: Programming Language :: Python :: 3.4
Classifier: Programming Language :: Python :: 3.5
Classifier: Programming Language :: Python :: 3.6
Classifier: Programming Language :: Python :: 3.7
Classifier: License :: OSI Approved :: MIT License
Classifier: Operating System :: OS Independent
Requires-Python: >=3.6
License-File: LICENSE
Requires-Dist: feedparser
Requires-Dist: beautifulsoup4
Requires-Dist: requests
Requires-Dist: dateparser
